[
  {
    "exercise_name": "link-me",
    "started_at": 1755625386.522324,
    "completed_at": 1755625386.842156,
    "comments": [
      "Great work with using git remote to add an upstream remote!"
    ],
    "status": "Completed"
  },
  {
    "exercise_name": "remote-control",
    "started_at": 1755623528.719732,
    "completed_at": 1755623592.569109,
    "comments": [
      "Great work setting up a public remote repository!"
    ],
    "status": "Completed"
  },
  {
    "exercise_name": "remote-control",
    "started_at": 1755624602.991673,
    "completed_at": 1755624625.102422,
    "comments": [
      "Great work setting up a public remote repository!"
    ],
    "status": "Completed"
  },
  {
    "exercise_name": "link-me",
    "started_at": 1755672735.332329,
    "completed_at": 1755672735.60821,
    "comments": [
      "Great work with using git remote to add an upstream remote!"
    ],
    "status": "Completed"
  },
  {
    "exercise_name": "push-over",
    "started_at": 1755672871.019416,
    "completed_at": 1755672881.005048,
    "comments": [
      "You might have forgotten to push your commit to the remote repository."
    ],
    "status": "Incomplete"
  },
  {
    "exercise_name": "link-me",
    "started_at": 1755674035.701631,
    "completed_at": 1755674035.73963,
    "comments": [
      "Great work with using git remote to add an upstream remote!"
    ],
    "status": "Completed"
  },
  {
    "exercise_name": "push-over",
    "started_at": 1755674081.070729,
    "completed_at": 1755674084.158103,
    "comments": [
      "You might have forgotten to push your commit to the remote repository."
    ],
    "status": "Incomplete"
  },
  {
    "exercise_name": "push-over",
    "started_at": 1755674122.086667,
    "completed_at": 1755674124.849914,
    "comments": [
      "Great work pushing changes to the remote!"
    ],
    "status": "Completed"
  },
  {
    "exercise_name": "ignoring-somethings",
    "started_at": 1755675133.970981,
    "completed_at": 1755675136.949862,
    "comments": [
      "You are not ignoring runaway.txt. Find where the file is and fix that."
    ],
    "status": "Incomplete"
  },
  {
    "exercise_name": "ignoring-somethings",
    "started_at": 1755675483.010048,
    "completed_at": 1755675486.233443,
    "comments": [
      "You are not ignoring runaway.txt. Find where the file is and fix that."
    ],
    "status": "Incomplete"
  },
  {
    "exercise_name": "ignoring-somethings",
    "started_at": 1755675712.836056,
    "completed_at": 1755675715.528527,
    "comments": [
      "You are not ignoring runaway.txt. Find where the file is and fix that."
    ],
    "status": "Incomplete"
  },
  {
    "exercise_name": "ignoring-somethings",
    "started_at": 1755675775.002145,
    "completed_at": 1755675777.68989,
    "comments": [
      "You are not ignoring runaway.txt. Find where the file is and fix that."
    ],
    "status": "Incomplete"
  },
  {
    "exercise_name": "ignoring-somethings",
    "started_at": 1755675860.978576,
    "completed_at": 1755675863.918829,
    "comments": [
      "You are not ignoring runaway.txt. Find where the file is and fix that."
    ],
    "status": "Incomplete"
  },
  {
    "exercise_name": "ignoring-somethings",
    "started_at": 1755675999.73741,
    "completed_at": 1755676002.436892,
    "comments": [
      "You are not ignoring runaway.txt. Find where the file is and fix that."
    ],
    "status": "Incomplete"
  },
  {
    "exercise_name": "ignoring-somethings",
    "started_at": 1755676049.728647,
    "completed_at": 1755676052.401973,
    "comments": [
      "You are not ignoring runaway.txt. Find where the file is and fix that."
    ],
    "status": "Incomplete"
  },
  {
    "exercise_name": "ignoring-somethings",
    "started_at": 1755676196.401897,
    "completed_at": 1755676199.290562,
    "comments": [
      "Great work using .gitignore!"
    ],
    "status": "Completed"
  },
  {
    "exercise_name": "fork-repo",
    "started_at": 1755690385.025576,
    "completed_at": 1755690386.776844,
    "comments": [
      "Great work creating a fork with Github!"
    ],
    "status": "Completed"
  },
  {
    "exercise_name": "clone-repo",
    "started_at": 1755690697.361031,
    "completed_at": 1755690699.103466,
    "comments": [
      "The upstream remote does not point to the original repository!"
    ],
    "status": "Incomplete"
  },
  {
    "exercise_name": "clone-repo",
    "started_at": 1755690787.614011,
    "completed_at": 1755690789.202391,
    "comments": [
      "Great work creating a clone of a fork from Github!"
    ],
    "status": "Completed"
  }
]